pydanilov/__init__.py
pydanilov/_danilov.py
pydanilov-0.0.7b8.dist-info/LICENSE.txt
pydanilov-0.0.7b8.dist-info/METADATA
pydanilov-0.0.7b8.dist-info/WHEEL
pydanilov-0.0.7b8.dist-info/top_level.txt
pydanilov-0.0.7b8.dist-info/RECORD
