Metadata-Version: 2.1
Name: pydanilov
Version: 0.0.7b8
Summary: pyDanilov is a Python3 implementation of the Danilov model, a semi-empirical model of the non-auroral Earth's ionosphere D-Region.
Home-page: https://gitlab.com/zolotov/pydanilov
Author: Denis Sakaev, Oleg Zolotov
Author-email: denissackaev@yandex.ru
License: Apache Software License
Keywords: lower ionosphere of the Earth,D-region,D-layer,model
Platform: UNKNOWN
Classifier: Development Status :: 2 - Pre-Alpha
Classifier: Intended Audience :: Science/Research
Classifier: Topic :: Scientific/Engineering :: Physics
Classifier: License :: OSI Approved :: Apache Software License
Classifier: Programming Language :: Python :: 3
Classifier: Programming Language :: Python :: 3.6
Classifier: Programming Language :: Python :: 3.7
Classifier: Programming Language :: Python :: 3.8
Classifier: Programming Language :: Python :: 3.9
Classifier: Programming Language :: Python :: 3 :: Only
License-File: LICENSE.txt
Requires-Dist: numpy
